Metadata-Version: 2.1
Name: discord-json-database
Version: 0.1.1
Summary: Easily manage a JSON database for a Discord bot
Author: Cypress4382
License-File: LICENSE
